tensorflow_mri-0.22.0.dist-info/top_level.txt
tensorflow_mri-0.22.0.dist-info/LICENSE
tensorflow_mri-0.22.0.dist-info/METADATA
tensorflow_mri-0.22.0.dist-info/RECORD
tensorflow_mri-0.22.0.dist-info/WHEEL
tensorflow_mri/__init__.py
tensorflow_mri/__about__.py
tensorflow_mri/_api/__init__.py
tensorflow_mri/_api/recon/__init__.py
tensorflow_mri/_api/models/__init__.py
tensorflow_mri/_api/metrics/__init__.py
tensorflow_mri/_api/convex/__init__.py
tensorflow_mri/_api/layers/__init__.py
tensorflow_mri/_api/array/__init__.py
tensorflow_mri/_api/io/__init__.py
tensorflow_mri/_api/summary/__init__.py
tensorflow_mri/_api/math/__init__.py
tensorflow_mri/_api/plot/__init__.py
tensorflow_mri/_api/initializers/__init__.py
tensorflow_mri/_api/coils/__init__.py
tensorflow_mri/_api/image/__init__.py
tensorflow_mri/_api/callbacks/__init__.py
tensorflow_mri/_api/optimize/__init__.py
tensorflow_mri/_api/signal/__init__.py
tensorflow_mri/_api/linalg/__init__.py
tensorflow_mri/_api/sampling/__init__.py
tensorflow_mri/_api/losses/__init__.py
tensorflow_mri/python/__init__.py
tensorflow_mri/python/util/tensor_util.py
tensorflow_mri/python/util/keras_util.py
tensorflow_mri/python/util/plot_util.py
tensorflow_mri/python/util/test_util.py
tensorflow_mri/python/util/nest_util.py
tensorflow_mri/python/util/check_util.py
tensorflow_mri/python/util/sys_util.py
tensorflow_mri/python/util/linalg_imaging.py
tensorflow_mri/python/util/layer_util.py
tensorflow_mri/python/util/prefer_static.py
tensorflow_mri/python/util/__init__.py
tensorflow_mri/python/util/model_util.py
tensorflow_mri/python/util/types_util.py
tensorflow_mri/python/util/api_util.py
tensorflow_mri/python/util/import_util.py
tensorflow_mri/python/util/deprecation.py
tensorflow_mri/python/util/linalg_ext.py
tensorflow_mri/python/util/io_util.py
tensorflow_mri/python/util/math_util.py
tensorflow_mri/python/util/data_util.py
tensorflow_mri/python/models/conv_blocks.py
tensorflow_mri/python/models/conv_endec.py
tensorflow_mri/python/models/__init__.py
tensorflow_mri/python/metrics/iqa_metrics.py
tensorflow_mri/python/metrics/confusion_metrics.py
tensorflow_mri/python/metrics/__init__.py
