Metadata-Version: 2.1
Name: tensorflow-mri
Version: 0.22.0
Summary: A collection of TensorFlow add-ons for computational MRI.
Home-page: https://github.com/mrphys/tensorflow-mri
Author: Javier Montalt Tordera
Author-email: javier.montalt@outlook.com
License: Apache 2.0
Keywords: tensorflow,mri,machine learning,ml
Classifier: Development Status :: 4 - Beta
Classifier: Environment :: GPU
Classifier: Environment :: GPU :: NVIDIA CUDA
Classifier: Intended Audience :: Developers
Classifier: Intended Audience :: Education
Classifier: Intended Audience :: Science/Research
Classifier: License :: OSI Approved :: Apache Software License
Classifier: Programming Language :: C++
Classifier: Programming Language :: Python :: 3
Classifier: Programming Language :: Python :: 3.7
Classifier: Programming Language :: Python :: 3.8
Classifier: Programming Language :: Python :: 3.9
Classifier: Programming Language :: Python :: 3.10
Classifier: Topic :: Scientific/Engineering :: Mathematics
Classifier: Topic :: Software Development :: Libraries
Classifier: Topic :: Software Development :: Libraries :: Python Modules
License-File: LICENSE
Requires-Dist: h5py
Requires-Dist: ismrmrd
Requires-Dist: matplotlib
Requires-Dist: numpy
Requires-Dist: plotly
Requires-Dist: PyWavelets
Requires-Dist: scipy
Requires-Dist: tensorboard
Requires-Dist: tensorflow (<2.11.0,>=2.10.0)
Requires-Dist: tensorflow-graphics
Requires-Dist: tensorflow-io (<0.28.0,>=0.27.0)
Requires-Dist: tensorflow-nufft (<0.11.0,>=0.10.0)
Requires-Dist: tensorflow-probability (<0.19.0,>=0.18.0)
